odoo/addons/partner_identification_disable/README.rst
odoo/addons/partner_identification_disable/__init__.py
odoo/addons/partner_identification_disable/__manifest__.py
odoo/addons/partner_identification_disable/i18n/es.po
odoo/addons/partner_identification_disable/models/__init__.py
odoo/addons/partner_identification_disable/models/res_partner_id_category.py
odoo/addons/partner_identification_disable/readme/CONFIGURE.md
odoo/addons/partner_identification_disable/readme/CONTRIBUTORS.md
odoo/addons/partner_identification_disable/readme/DESCRIPTION.md
odoo/addons/partner_identification_disable/static/description/icon.png
odoo/addons/partner_identification_disable/static/description/index.html
odoo/addons/partner_identification_disable/views/res_partner_id_category_view.xml
odoo_addon_partner_identification_disable-16.0.1.0.0.2.dist-info/METADATA
odoo_addon_partner_identification_disable-16.0.1.0.0.2.dist-info/WHEEL
odoo_addon_partner_identification_disable-16.0.1.0.0.2.dist-info/top_level.txt
odoo_addon_partner_identification_disable-16.0.1.0.0.2.dist-info/RECORD
